ur_gadget/__init__.py
ur_gadget/datetime_intel.py
ur_gadget/gadget.py
ur_gadget-0.0.4.dist-info/LICENSE
ur_gadget-0.0.4.dist-info/METADATA
ur_gadget-0.0.4.dist-info/WHEEL
ur_gadget-0.0.4.dist-info/top_level.txt
ur_gadget-0.0.4.dist-info/RECORD
