Metadata-Version: 2.1
Name: ur-gadget
Version: 0.0.4
Summary: Useful gadgets for your python projects
Home-page: https://github.com/thinh-vu/vnnews
Author: Thinh Vu
Author-email: mrthinh@live.com
Classifier: Programming Language :: Python :: 3
Classifier: License :: OSI Approved :: MIT License
Classifier: Operating System :: OS Independent
Requires-Python: >=3.7
License-File: LICENSE
Requires-Dist: trafilatura
